LICENSE.txt
MANIFEST.in
README.md
pyproject.toml
requirements.txt
setup.py
deepcave/__init__.py
deepcave/cli.py
deepcave/config.py
deepcave/constants.py
deepcave/custom_queue.py
deepcave/open.py
deepcave/py.typed
deepcave/server.py
deepcave/start.sh
deepcave/worker.py
deepcave.egg-info/PKG-INFO
deepcave.egg-info/SOURCES.txt
deepcave.egg-info/dependency_links.txt
deepcave.egg-info/entry_points.txt
deepcave.egg-info/requires.txt
deepcave.egg-info/top_level.txt
deepcave/assets/custom.css
deepcave/docs/api.rst
deepcave/docs/faq.rst
deepcave/docs/getting_started.rst
deepcave/docs/glossary.rst
deepcave/docs/how_to_contribute.rst
deepcave/docs/index.rst
deepcave/docs/installation.rst
deepcave/docs/redis.rst
deepcave/docs/converters/amltk.rst
deepcave/docs/converters/bohb.rst
deepcave/docs/converters/custom_converters.rst
deepcave/docs/converters/dataframe.rst
deepcave/docs/converters/deepcave.rst
deepcave/docs/converters/index.rst
deepcave/docs/converters/optuna.rst
deepcave/docs/converters/raytune.rst
deepcave/docs/converters/smac.rst
deepcave/docs/plugins/ablation_paths.rst
deepcave/docs/plugins/budget_correlation.rst
deepcave/docs/plugins/configuration_cube.rst
deepcave/docs/plugins/configuration_footprint.rst
deepcave/docs/plugins/configurations.rst
deepcave/docs/plugins/cost_over_time.rst
deepcave/docs/plugins/custom_plugins.rst
deepcave/docs/plugins/importances.rst
deepcave/docs/plugins/index.rst
deepcave/docs/plugins/overview.rst
deepcave/docs/plugins/parallel_coordinates.rst
deepcave/docs/plugins/pareto_front.rst
deepcave/docs/plugins/partial_dependencies.rst
deepcave/docs/plugins/symbolic_explanations.rst
deepcave/evaluators/__init__.py
deepcave/evaluators/ablation.py
deepcave/evaluators/fanova.py
deepcave/evaluators/footprint.py
deepcave/evaluators/lpi.py
deepcave/evaluators/mo_ablation.py
deepcave/evaluators/mo_fanova.py
deepcave/evaluators/mo_lpi.py
deepcave/evaluators/epm/__init__.py
deepcave/evaluators/epm/fanova_forest.py
deepcave/evaluators/epm/random_forest.py
deepcave/evaluators/epm/random_forest_surrogate.py
deepcave/evaluators/epm/utils.py
deepcave/layouts/__init__.py
deepcave/layouts/general.py
deepcave/layouts/header.py
