Metadata-Version: 2.1
Name: deepcave
Version: 1.4
Summary: An interactive framework to visualize and analyze your AutoML process in real-time.
Home-page: https://www.automl.org
Author-email: m.wever@ai.uni-hannover.de
License: Apache-2.0
Project-URL: Documentation, https://github.com/automl/deepcave
Project-URL: Source Code, https://github.com/automl/deepcave
Platform: Linux
Classifier: Programming Language :: Python :: 3.9
Classifier: Programming Language :: Python :: 3.10
Classifier: Development Status :: 3 - Alpha
Classifier: Natural Language :: English
Classifier: Environment :: Console
Classifier: Intended Audience :: Developers
Classifier: Intended Audience :: Education
Classifier: Intended Audience :: Science/Research
Classifier: License :: OSI Approved :: Apache Software License
Classifier: Operating System :: POSIX :: Linux
Classifier: Topic :: Scientific/Engineering :: Artificial Intelligence
Classifier: Topic :: Scientific/Engineering
Classifier: Topic :: Software Development
Requires-Python: >=3.9, <3.11
License-File: LICENSE.txt
Requires-Dist: wheel>=0.41.2
Requires-Dist: setuptools==68.2.2
Requires-Dist: absl-py>=1.0.0
Requires-Dist: jsonlines>=3.0.0
Requires-Dist: pandas>=1.3.4
Requires-Dist: matplotlib==3.9.0
Requires-Dist: seaborn>=0.13.0
Requires-Dist: pyyaml>=6.0.1
Requires-Dist: kaleido>=0.2.1
Requires-Dist: gplearn>=0.4.2
Requires-Dist: sympy>=1.12
Requires-Dist: requests>=2.31.0
Requires-Dist: ConfigSpace==1.2.0
Requires-Dist: pyrfr>=0.9.0
Requires-Dist: dash==2.0.0
Requires-Dist: dash-extensions==0.0.71
Requires-Dist: dash-bootstrap-components==1.0.3
Requires-Dist: redis>=4.1.4
Requires-Dist: rq==1.10.1
Requires-Dist: plotly==5.24.1
Requires-Dist: werkzeug==2.0.3
Requires-Dist: pyarrow==19.0.1
Requires-Dist: fastparquet==2024.5.0
Requires-Dist: pyPDPPartitioner>=0.1.9
Provides-Extra: dev
Requires-Dist: pytest>=4.6; extra == "dev"
Requires-Dist: pytest-cov>=4.1.0; extra == "dev"
Requires-Dist: pytest-xdist>=3.3.1; extra == "dev"
Requires-Dist: pytest-timeout>=2.2.0; extra == "dev"
Requires-Dist: mypy>=1.6.1; extra == "dev"
Requires-Dist: isort>=5.12.0; extra == "dev"
Requires-Dist: black>=23.11.0; extra == "dev"
Requires-Dist: pydocstyle>=6.3.0; extra == "dev"
Requires-Dist: pre-commit>=3.5.0; extra == "dev"
Requires-Dist: flake8>=6.1.0; extra == "dev"
Requires-Dist: rq==1.10.1; extra == "dev"
Requires-Dist: pyPDPPartitioner>=0.1.9; extra == "dev"
Requires-Dist: automl-sphinx-theme>=0.1.10; extra == "dev"
Provides-Extra: examples
Requires-Dist: torch>=2.1.0; extra == "examples"
Requires-Dist: torchvision>=0.16.0; extra == "examples"
Requires-Dist: pytorch-lightning>=2.1.1; extra == "examples"
Provides-Extra: optuna
Requires-Dist: optuna==3.6.1; extra == "optuna"
Provides-Extra: bohb
Requires-Dist: hpbandster==0.7.4; extra == "bohb"
Provides-Extra: raytune
Requires-Dist: ray[tune]==2.45.0; extra == "raytune"
